{"tests": [{"site_id": 6, "type_of_test": 20, "rating": 5.0, "rating_sec": 5.0, "rating_perf": -1.0, "rating_a11y": -1.0, "rating_stand": -1.0, "date": "2023-03-20T22:00:08.589284", "report": "- The website is great on privacy!\n- Result generated: 2023-03-20 21:59:58 Etc/UTC (Cached for 24 hours)\n", "report_sec": "- HTTPS by default: is good! ( 5.00 rating )\r\n- HTTP Strict Transport Security HSTS: is good! ( 5.00 rating )\r\n- Content Security Policy: is good! ( 5.00 rating )\r\n- Reporting CSP Certificate Transparency Network Error Logging: is good! ( 5.00 rating )\r\n- Referrer Policy: is good! ( 5.00 rating )\r\n- Subresource Integrity SRI: is good! ( 5.00 rating )\r\n- HTTP headers: is good! ( 5.00 rating )\r\n- Cookies: is good! ( 5.00 rating )\r\n", "report_perf": "", "report_a11y": "", "report_stand": "", "data": "{}"}, {"site_id": 7, "type_of_test": 20, "rating": 2.44, "rating_sec": 2.44, "rating_perf": -1.0, "rating_a11y": -1.0, "rating_stand": -1.0, "date": "2023-03-20T22:00:30.164673", "report": "- Rather poor on user privacy.\n- Result generated: 2023-03-20 22:00:23 Etc/UTC (Cached for 24 hours)\n", "report_sec": "- HTTPS by default: is good! ( 5.00 rating )\r\n- Strict Transport Security: is pretty bad. ( 1.00 rating )\r\n- Content Security Policy: is pretty bad. ( 1.00 rating )\r\n- Reporting CSP Certificate Transparency Network Error Logging: is good! ( 5.00 rating )\r\n- Referrer Policy: is pretty bad. ( 1.00 rating )\r\n- Subresource Integrity SRI: is pretty bad. ( 1.00 rating )\r\n- HTTP headers: is ok, with 1 error(s) and 0 warning(s). ( 4.50 rating )\r\n- Cookies: is ok, with 51 error(s) and 0 warning(s). ( 1.00 rating )\r\n", "report_perf": "", "report_a11y": "", "report_stand": "", "data": "{}"}, {"site_id": 8, "type_of_test": 20, "rating": 2.44, "rating_sec": 2.44, "rating_perf": -1.0, "rating_a11y": -1.0, "rating_stand": -1.0, "date": "2023-03-20T22:00:51.731290", "report": "- Rather poor on user privacy.\n- Result generated: 2023-03-20 22:00:43 Etc/UTC (Cached for 24 hours)\n", "report_sec": "- HTTPS by default: is good! ( 5.00 rating )\r\n- HTTP Strict Transport Security HSTS: is pretty bad. ( 1.00 rating )\r\n- Content Security Policy: is pretty bad. ( 1.00 rating )\r\n- Reporting CSP Certificate Transparency Network Error Logging: is good! ( 5.00 rating )\r\n- Referrer Policy: is pretty bad. ( 1.00 rating )\r\n- Subresource Integrity SRI: is pretty bad. ( 1.00 rating )\r\n- HTTP headers: is ok, with 1 error(s) and 0 warning(s). ( 4.50 rating )\r\n- Cookies: is ok, with 67 error(s) and 0 warning(s). ( 1.00 rating )\r\n", "report_perf": "", "report_a11y": "", "report_stand": "", "data": "{}"}, {"site_id": 9, "type_of_test": 20, "rating": 2.91, "rating_sec": 2.91, "rating_perf": -1.0, "rating_a11y": -1.0, "rating_stand": -1.0, "date": "2023-03-20T22:01:13.247551", "report": "- Rather poor on user privacy.\n- Result generated: 2023-03-20 22:01:07 Etc/UTC (Cached for 24 hours)\n", "report_sec": "- HTTPS by default: is good! ( 5.00 rating )\r\n- HTTP Strict Transport Security HSTS: is ok, with 1 error(s) and 1 warning(s). ( 4.25 rating )\r\n- Content Security Policy: is pretty bad. ( 1.00 rating )\r\n- Reporting CSP Certificate Transparency Network Error Logging: is good! ( 5.00 rating )\r\n- Referrer Policy: is pretty bad. ( 1.00 rating )\r\n- Subresource Integrity SRI: is pretty bad. ( 1.00 rating )\r\n- HTTP headers: is good! ( 5.00 rating )\r\n- Cookies: is ok, with 20 error(s) and 0 warning(s). ( 1.00 rating )\r\n", "report_perf": "", "report_a11y": "", "report_stand": "", "data": "{}"}, {"site_id": 11, "type_of_test": 20, "rating": 3.03, "rating_sec": 3.03, "rating_perf": -1.0, "rating_a11y": -1.0, "rating_stand": -1.0, "date": "2023-03-20T22:01:34.762876", "report": "- Ok integrity but should get better.\n- Result generated: 2023-03-20 22:01:25 Etc/UTC (Cached for 24 hours)\n", "report_sec": "- HTTPS by default: is good! ( 5.00 rating )\r\n- HTTP Strict Transport Security HSTS: is ok, with 1 error(s) and 1 warning(s). ( 4.25 rating )\r\n- Content Security Policy: is pretty bad. ( 1.00 rating )\r\n- Reporting CSP Certificate Transparency Network Error Logging: is not that good. ( 2.50 rating )\r\n- Referrer Policy: is pretty bad. ( 1.00 rating )\r\n- Subresource Integrity SRI: is pretty bad. ( 1.00 rating )\r\n- HTTP headers: is ok, with 1 error(s) and 0 warning(s). ( 4.50 rating )\r\n- Cookies: is good! ( 5.00 rating )\r\n", "report_perf": "", "report_a11y": "", "report_stand": "", "data": "{}"}, {"site_id": 12, "type_of_test": 20, "rating": 2.81, "rating_sec": 2.81, "rating_perf": -1.0, "rating_a11y": -1.0, "rating_stand": -1.0, "date": "2023-03-20T22:01:56.271764", "report": "- Rather poor on user privacy.\n- Result generated: 2023-03-20 22:01:48 Etc/UTC (Cached for 24 hours)\n", "report_sec": "- HTTPS by default: is good! ( 5.00 rating )\r\n- HTTP Strict Transport Security HSTS: is ok, with 1 error(s) and 0 warning(s). ( 4.50 rating )\r\n- Content Security Policy: is pretty bad. ( 1.00 rating )\r\n- Reporting CSP Certificate Transparency Network Error Logging: is not that good. ( 2.50 rating )\r\n- Referrer Policy: is not that good. ( 2.50 rating )\r\n- Subresource Integrity SRI: is pretty bad. ( 1.00 rating )\r\n- HTTP headers: is good! ( 5.00 rating )\r\n- Cookies: is ok, with 8 error(s) and 0 warning(s). ( 1.00 rating )\r\n", "report_perf": "", "report_a11y": "", "report_stand": "", "data": "{}"}, {"site_id": 13, "type_of_test": 20, "rating": 2.44, "rating_sec": 2.44, "rating_perf": -1.0, "rating_a11y": -1.0, "rating_stand": -1.0, "date": "2023-03-20T22:02:17.805274", "report": "- Rather poor on user privacy.\n- Result generated: 2023-03-20 22:02:11 Etc/UTC (Cached for 24 hours)\n", "report_sec": "- HTTPS by default: is good! ( 5.00 rating )\r\n- Strict Transport Security: is pretty bad. ( 1.00 rating )\r\n- Content Security Policy: is pretty bad. ( 1.00 rating )\r\n- Reporting CSP Certificate Transparency Network Error Logging: is good! ( 5.00 rating )\r\n- Referrer Policy: is pretty bad. ( 1.00 rating )\r\n- Subresource Integrity SRI: is pretty bad. ( 1.00 rating )\r\n- HTTP headers: is ok, with 1 error(s) and 0 warning(s). ( 4.50 rating )\r\n- Cookies: is ok, with 9 error(s) and 0 warning(s). ( 1.00 rating )\r\n", "report_perf": "", "report_a11y": "", "report_stand": "", "data": "{}"}, {"site_id": 16, "type_of_test": 20, "rating": 2.12, "rating_sec": 2.12, "rating_perf": -1.0, "rating_a11y": -1.0, "rating_stand": -1.0, "date": "2023-03-20T22:02:39.342284", "report": "- Rather poor on user privacy.\n- Result generated: 2023-03-20 22:02:30 Etc/UTC (Cached for 24 hours)\n", "report_sec": "- HTTPS by default: is good! ( 5.00 rating )\r\n- Strict Transport Security: is pretty bad. ( 1.00 rating )\r\n- Content Security Policy: is pretty bad. ( 1.00 rating )\r\n- Reporting CSP Certificate Transparency Network Error Logging: is not that good. ( 2.50 rating )\r\n- Referrer Policy: is pretty bad. ( 1.00 rating )\r\n- Subresource Integrity SRI: is pretty bad. ( 1.00 rating )\r\n- HTTP headers: is ok, with 1 error(s) and 0 warning(s). ( 4.50 rating )\r\n- Cookies: is ok, with 9 error(s) and 0 warning(s). ( 1.00 rating )\r\n", "report_perf": "", "report_a11y": "", "report_stand": "", "data": "{}"}, {"site_id": 17, "type_of_test": 20, "rating": 2.75, "rating_sec": 2.75, "rating_perf": -1.0, "rating_a11y": -1.0, "rating_stand": -1.0, "date": "2023-03-20T22:03:00.879275", "report": "- Rather poor on user privacy.\n- Result generated: 2023-03-20 22:02:52 Etc/UTC (Cached for 24 hours)\n", "report_sec": "- HTTPS by default: is good! ( 5.00 rating )\r\n- HTTP Strict Transport Security HSTS: is ok, with 3 error(s) and 0 warning(s). ( 3.50 rating )\r\n- Content Security Policy: is pretty bad. ( 1.00 rating )\r\n- Reporting CSP Certificate Transparency Network Error Logging: is good! ( 5.00 rating )\r\n- Referrer Policy: is pretty bad. ( 1.00 rating )\r\n- Subresource Integrity SRI: is pretty bad. ( 1.00 rating )\r\n- HTTP headers: is ok, with 1 error(s) and 0 warning(s). ( 4.50 rating )\r\n- Cookies: is ok, with 9 error(s) and 0 warning(s). ( 1.00 rating )\r\n", "report_perf": "", "report_a11y": "", "report_stand": "", "data": "{}"}, {"site_id": 19, "type_of_test": 20, "rating": 3.0, "rating_sec": 3.0, "rating_perf": -1.0, "rating_a11y": -1.0, "rating_stand": -1.0, "date": "2023-03-20T22:03:22.383728", "report": "- Ok integrity but should get better.\n- Result generated: 2023-03-20 22:03:14 Etc/UTC (Cached for 24 hours)\n", "report_sec": "- HTTPS by default: is good! ( 5.00 rating )\r\n- HTTP Strict Transport Security HSTS: is ok, with 2 error(s) and 0 warning(s). ( 4.00 rating )\r\n- Content Security Policy: is pretty bad. ( 1.00 rating )\r\n- Reporting CSP Certificate Transparency Network Error Logging: is not that good. ( 2.50 rating )\r\n- Referrer Policy: is pretty bad. ( 1.00 rating )\r\n- Subresource Integrity SRI: is pretty bad. ( 1.00 rating )\r\n- HTTP headers: is ok, with 1 error(s) and 0 warning(s). ( 4.50 rating )\r\n- Cookies: is good! ( 5.00 rating )\r\n", "report_perf": "", "report_a11y": "", "report_stand": "", "data": "{}"}, {"site_id": 21, "type_of_test": 20, "rating": 2.88, "rating_sec": 2.88, "rating_perf": -1.0, "rating_a11y": -1.0, "rating_stand": -1.0, "date": "2023-03-20T22:03:43.888380", "report": "- Rather poor on user privacy.\n- Result generated: 2023-03-20 22:03:34 Etc/UTC (Cached for 24 hours)\n", "report_sec": "- HTTPS by default: is good! ( 5.00 rating )\r\n- Strict Transport Security: is pretty bad. ( 1.00 rating )\r\n- Content Security Policy: is pretty bad. ( 1.00 rating )\r\n- Reporting CSP Certificate Transparency Network Error Logging: is good! ( 5.00 rating )\r\n- Referrer Policy: is pretty bad. ( 1.00 rating )\r\n- Subresource Integrity SRI: is pretty bad. ( 1.00 rating )\r\n- HTTP headers: is ok, with 1 error(s) and 0 warning(s). ( 4.50 rating )\r\n- Cookies: is ok, with 1 error(s) and 0 warning(s). ( 4.50 rating )\r\n", "report_perf": "", "report_a11y": "", "report_stand": "", "data": "{}"}, {"site_id": 22, "type_of_test": 20, "rating": 2.44, "rating_sec": 2.44, "rating_perf": -1.0, "rating_a11y": -1.0, "rating_stand": -1.0, "date": "2023-03-20T22:04:05.394714", "report": "- Rather poor on user privacy.\n- Result generated: 2023-03-20 22:03:57 Etc/UTC (Cached for 24 hours)\n", "report_sec": "- HTTPS by default: is good! ( 5.00 rating )\r\n- Strict Transport Security: is pretty bad. ( 1.00 rating )\r\n- Content Security Policy: is pretty bad. ( 1.00 rating )\r\n- Reporting CSP Certificate Transparency Network Error Logging: is good! ( 5.00 rating )\r\n- Referrer Policy: is pretty bad. ( 1.00 rating )\r\n- Subresource Integrity SRI: is pretty bad. ( 1.00 rating )\r\n- HTTP headers: is ok, with 1 error(s) and 0 warning(s). ( 4.50 rating )\r\n- Cookies: is ok, with 15 error(s) and 0 warning(s). ( 1.00 rating )\r\n", "report_perf": "", "report_a11y": "", "report_stand": "", "data": "{}"}, {"site_id": 23, "type_of_test": 20, "rating": 2.21, "rating_sec": 2.21, "rating_perf": -1.0, "rating_a11y": -1.0, "rating_stand": -1.0, "date": "2023-03-20T22:04:26.918745", "report": "- Rather poor on user privacy.\n- Result generated: 2023-03-20 22:04:22 Etc/UTC (Cached for 24 hours)\n", "report_sec": "- Insecure: HTTPS not used by default: is pretty bad. ( 1.00 rating )\r\n- Content Security Policy: is pretty bad. ( 1.00 rating )\r\n- Reporting CSP Certificate Transparency Network Error Logging: is good! ( 5.00 rating )\r\n- Referrer Policy: is pretty bad. ( 1.00 rating )\r\n- Subresource Integrity SRI: is pretty bad. ( 1.00 rating )\r\n- HTTP headers: is ok, with 1 error(s) and 0 warning(s). ( 4.50 rating )\r\n- Cookies: is ok, with 6 error(s) and 0 warning(s). ( 2.00 rating )\r\n", "report_perf": "", "report_a11y": "", "report_stand": "", "data": "{}"}, {"site_id": 24, "type_of_test": 20, "rating": 2.44, "rating_sec": 2.44, "rating_perf": -1.0, "rating_a11y": -1.0, "rating_stand": -1.0, "date": "2023-03-20T22:04:48.415189", "report": "- Rather poor on user privacy.\n- Result generated: 2023-03-20 22:04:43 Etc/UTC (Cached for 24 hours)\n", "report_sec": "- HTTPS by default: is good! ( 5.00 rating )\r\n- Strict Transport Security: is pretty bad. ( 1.00 rating )\r\n- Content Security Policy: is pretty bad. ( 1.00 rating )\r\n- Reporting CSP Certificate Transparency Network Error Logging: is good! ( 5.00 rating )\r\n- Referrer Policy: is pretty bad. ( 1.00 rating )\r\n- Subresource Integrity SRI: is pretty bad. ( 1.00 rating )\r\n- HTTP headers: is ok, with 1 error(s) and 0 warning(s). ( 4.50 rating )\r\n- Cookies: is ok, with 9 error(s) and 0 warning(s). ( 1.00 rating )\r\n", "report_perf": "", "report_a11y": "", "report_stand": "", "data": "{}"}, {"site_id": 25, "type_of_test": 20, "rating": 2.75, "rating_sec": 2.75, "rating_perf": -1.0, "rating_a11y": -1.0, "rating_stand": -1.0, "date": "2023-03-20T22:05:09.927477", "report": "- Rather poor on user privacy.\n- Result generated: 2023-03-20 22:05:00 Etc/UTC (Cached for 24 hours)\n", "report_sec": "- HTTPS by default: is good! ( 5.00 rating )\r\n- HTTP Strict Transport Security HSTS: is ok, with 3 error(s) and 0 warning(s). ( 3.50 rating )\r\n- Content Security Policy: is pretty bad. ( 1.00 rating )\r\n- Reporting CSP Certificate Transparency Network Error Logging: is good! ( 5.00 rating )\r\n- Referrer Policy: is pretty bad. ( 1.00 rating )\r\n- Subresource Integrity SRI: is pretty bad. ( 1.00 rating )\r\n- HTTP headers: is ok, with 1 error(s) and 0 warning(s). ( 4.50 rating )\r\n- Cookies: is ok, with 21 error(s) and 0 warning(s). ( 1.00 rating )\r\n", "report_perf": "", "report_a11y": "", "report_stand": "", "data": "{}"}, {"site_id": 27, "type_of_test": 20, "rating": 2.44, "rating_sec": 2.44, "rating_perf": -1.0, "rating_a11y": -1.0, "rating_stand": -1.0, "date": "2023-03-20T22:05:31.513462", "report": "- Rather poor on user privacy.\n- Result generated: 2023-03-20 22:05:22 Etc/UTC (Cached for 24 hours)\n", "report_sec": "- HTTPS by default: is good! ( 5.00 rating )\r\n- Strict Transport Security: is pretty bad. ( 1.00 rating )\r\n- Content Security Policy: is pretty bad. ( 1.00 rating )\r\n- Reporting CSP Certificate Transparency Network Error Logging: is good! ( 5.00 rating )\r\n- Referrer Policy: is pretty bad. ( 1.00 rating )\r\n- Subresource Integrity SRI: is pretty bad. ( 1.00 rating )\r\n- HTTP headers: is ok, with 1 error(s) and 0 warning(s). ( 4.50 rating )\r\n- Cookies: is ok, with 9 error(s) and 0 warning(s). ( 1.00 rating )\r\n", "report_perf": "", "report_a11y": "", "report_stand": "", "data": "{}"}, {"site_id": 28, "type_of_test": 20, "rating": 4.25, "rating_sec": 4.25, "rating_perf": -1.0, "rating_a11y": -1.0, "rating_stand": -1.0, "date": "2023-03-20T22:05:53.009988", "report": "- The site could be better, but is pretty good.\n- Result generated: 2023-03-20 22:05:43 Etc/UTC (Cached for 24 hours)\n", "report_sec": "- HTTPS by default: is good! ( 5.00 rating )\r\n- HTTP Strict Transport Security HSTS: is ok, with 3 error(s) and 0 warning(s). ( 3.50 rating )\r\n- Content Security Policy: is ok, with 4 error(s) and 0 warning(s). ( 3.00 rating )\r\n- Reporting CSP Certificate Transparency Network Error Logging: is not that good. ( 2.50 rating )\r\n- Referrer Policy: is good! ( 5.00 rating )\r\n- Subresource Integrity SRI: is good! ( 5.00 rating )\r\n- HTTP headers: is good! ( 5.00 rating )\r\n- Cookies: is good! ( 5.00 rating )\r\n", "report_perf": "", "report_a11y": "", "report_stand": "", "data": "{}"}, {"site_id": 29, "type_of_test": 20, "rating": 2.69, "rating_sec": 2.69, "rating_perf": -1.0, "rating_a11y": -1.0, "rating_stand": -1.0, "date": "2023-03-20T22:06:14.524898", "report": "- Rather poor on user privacy.\n- Result generated: 2023-03-20 22:06:07 Etc/UTC (Cached for 24 hours)\n", "report_sec": "- HTTPS by default: is good! ( 5.00 rating )\r\n- HTTP Strict Transport Security HSTS: is pretty bad. ( 1.00 rating )\r\n- Content Security Policy: is pretty bad. ( 1.00 rating )\r\n- Reporting CSP Certificate Transparency Network Error Logging: is good! ( 5.00 rating )\r\n- Referrer Policy: is not that good. ( 2.50 rating )\r\n- Subresource Integrity SRI: is pretty bad. ( 1.00 rating )\r\n- HTTP headers: is good! ( 5.00 rating )\r\n- Cookies: is ok, with 20 error(s) and 0 warning(s). ( 1.00 rating )\r\n", "report_perf": "", "report_a11y": "", "report_stand": "", "data": "{}"}, {"site_id": 30, "type_of_test": 20, "rating": 3.06, "rating_sec": 3.06, "rating_perf": -1.0, "rating_a11y": -1.0, "rating_stand": -1.0, "date": "2023-03-20T22:06:36.024349", "report": "- Ok integrity but should get better.\n- Result generated: 2023-03-20 22:06:26 Etc/UTC (Cached for 24 hours)\n", "report_sec": "- HTTPS by default: is good! ( 5.00 rating )\r\n- HTTP Strict Transport Security HSTS: is ok, with 2 error(s) and 0 warning(s). ( 4.00 rating )\r\n- Content Security Policy: is pretty bad. ( 1.00 rating )\r\n- Reporting CSP Certificate Transparency Network Error Logging: is good! ( 5.00 rating )\r\n- Referrer Policy: is not that good. ( 2.50 rating )\r\n- Subresource Integrity SRI: is pretty bad. ( 1.00 rating )\r\n- HTTP headers: is good! ( 5.00 rating )\r\n- Cookies: is ok, with 12 error(s) and 0 warning(s). ( 1.00 rating )\r\n", "report_perf": "", "report_a11y": "", "report_stand": "", "data": "{}"}, {"site_id": 31, "type_of_test": 20, "rating": 3.31, "rating_sec": 3.31, "rating_perf": -1.0, "rating_a11y": -1.0, "rating_stand": -1.0, "date": "2023-03-20T22:06:57.521000", "report": "- Ok integrity but should get better.\n- Result generated: 2023-03-20 22:06:48 Etc/UTC (Cached for 24 hours)\n", "report_sec": "- HTTPS by default: is good! ( 5.00 rating )\r\n- HTTP Strict Transport Security HSTS: is ok, with 2 error(s) and 0 warning(s). ( 4.00 rating )\r\n- Content Security Policy: is pretty bad. ( 1.00 rating )\r\n- Reporting CSP Certificate Transparency Network Error Logging: is good! ( 5.00 rating )\r\n- Referrer Policy: is pretty bad. ( 1.00 rating )\r\n- Subresource Integrity SRI: is pretty bad. ( 1.00 rating )\r\n- HTTP headers: is ok, with 1 error(s) and 0 warning(s). ( 4.50 rating )\r\n- Cookies: is good! ( 5.00 rating )\r\n", "report_perf": "", "report_a11y": "", "report_stand": "", "data": "{}"}, {"site_id": 32, "type_of_test": 20, "rating": 2.07, "rating_sec": 2.07, "rating_perf": -1.0, "rating_a11y": -1.0, "rating_stand": -1.0, "date": "2023-03-20T22:07:19.007544", "report": "- Rather poor on user privacy.\n- Result generated: 2023-03-20 22:07:10 Etc/UTC (Cached for 24 hours)\n", "report_sec": "- Insecure: HTTPS not used by default: is pretty bad. ( 1.00 rating )\r\n- Content Security Policy: is pretty bad. ( 1.00 rating )\r\n- Reporting CSP Certificate Transparency Network Error Logging: is good! ( 5.00 rating )\r\n- Referrer Policy: is pretty bad. ( 1.00 rating )\r\n- Subresource Integrity SRI: is pretty bad. ( 1.00 rating )\r\n- HTTP headers: is ok, with 1 error(s) and 0 warning(s). ( 4.50 rating )\r\n- Cookies: is ok, with 12 error(s) and 0 warning(s). ( 1.00 rating )\r\n", "report_perf": "", "report_a11y": "", "report_stand": "", "data": "{}"}, {"site_id": 33, "type_of_test": 20, "rating": 2.12, "rating_sec": 2.12, "rating_perf": -1.0, "rating_a11y": -1.0, "rating_stand": -1.0, "date": "2023-03-20T22:07:40.513950", "report": "- Rather poor on user privacy.\n- Result generated: 2023-03-20 22:07:31 Etc/UTC (Cached for 24 hours)\n", "report_sec": "- HTTPS by default: is good! ( 5.00 rating )\r\n- HTTP Strict Transport Security HSTS: is pretty bad. ( 1.00 rating )\r\n- Content Security Policy: is pretty bad. ( 1.00 rating )\r\n- Reporting CSP Certificate Transparency Network Error Logging: is not that good. ( 2.50 rating )\r\n- Referrer Policy: is pretty bad. ( 1.00 rating )\r\n- Subresource Integrity SRI: is pretty bad. ( 1.00 rating )\r\n- HTTP headers: is ok, with 1 error(s) and 0 warning(s). ( 4.50 rating )\r\n- Cookies: is ok, with 8 error(s) and 0 warning(s). ( 1.00 rating )\r\n", "report_perf": "", "report_a11y": "", "report_stand": "", "data": "{}"}, {"site_id": 35, "type_of_test": 20, "rating": 2.75, "rating_sec": 2.75, "rating_perf": -1.0, "rating_a11y": -1.0, "rating_stand": -1.0, "date": "2023-03-20T22:08:02.016760", "report": "- Rather poor on user privacy.\n- Result generated: 2023-03-20 22:07:55 Etc/UTC (Cached for 24 hours)\n", "report_sec": "- HTTPS by default: is good! ( 5.00 rating )\r\n- HTTP Strict Transport Security HSTS: is pretty bad. ( 1.00 rating )\r\n- Content Security Policy: is pretty bad. ( 1.00 rating )\r\n- Reporting CSP Certificate Transparency Network Error Logging: is not that good. ( 2.50 rating )\r\n- Referrer Policy: is not that good. ( 2.50 rating )\r\n- Subresource Integrity SRI: is pretty bad. ( 1.00 rating )\r\n- HTTP headers: is good! ( 5.00 rating )\r\n- Cookies: is ok, with 2 error(s) and 0 warning(s). ( 4.00 rating )\r\n", "report_perf": "", "report_a11y": "", "report_stand": "", "data": "{}"}, {"site_id": 36, "type_of_test": 20, "rating": 2.75, "rating_sec": 2.75, "rating_perf": -1.0, "rating_a11y": -1.0, "rating_stand": -1.0, "date": "2023-03-20T22:08:23.550135", "report": "- Rather poor on user privacy.\n- Result generated: 2023-03-20 22:08:14 Etc/UTC (Cached for 24 hours)\n", "report_sec": "- HTTPS by default: is good! ( 5.00 rating )\r\n- Strict Transport Security: is pretty bad. ( 1.00 rating )\r\n- Content Security Policy: is pretty bad. ( 1.00 rating )\r\n- Reporting CSP Certificate Transparency Network Error Logging: is good! ( 5.00 rating )\r\n- Referrer Policy: is pretty bad. ( 1.00 rating )\r\n- Subresource Integrity SRI: is pretty bad. ( 1.00 rating )\r\n- HTTP headers: is ok, with 1 error(s) and 0 warning(s). ( 4.50 rating )\r\n- Cookies: is ok, with 3 error(s) and 0 warning(s). ( 3.50 rating )\r\n", "report_perf": "", "report_a11y": "", "report_stand": "", "data": "{}"}, {"site_id": 37, "type_of_test": 20, "rating": 2.44, "rating_sec": 2.44, "rating_perf": -1.0, "rating_a11y": -1.0, "rating_stand": -1.0, "date": "2023-03-20T22:08:45.080407", "report": "- Rather poor on user privacy.\n- Result generated: 2023-03-20 22:08:35 Etc/UTC (Cached for 24 hours)\n", "report_sec": "- HTTPS by default: is good! ( 5.00 rating )\r\n- Strict Transport Security: is pretty bad. ( 1.00 rating )\r\n- Content Security Policy: is pretty bad. ( 1.00 rating )\r\n- Reporting CSP Certificate Transparency Network Error Logging: is good! ( 5.00 rating )\r\n- Referrer Policy: is pretty bad. ( 1.00 rating )\r\n- Subresource Integrity SRI: is pretty bad. ( 1.00 rating )\r\n- HTTP headers: is ok, with 1 error(s) and 0 warning(s). ( 4.50 rating )\r\n- Cookies: is ok, with 15 error(s) and 0 warning(s). ( 1.00 rating )\r\n", "report_perf": "", "report_a11y": "", "report_stand": "", "data": "{}"}, {"site_id": 38, "type_of_test": 20, "rating": -1.0, "rating_sec": -1.0, "rating_perf": -1.0, "rating_a11y": -1.0, "rating_stand": -1.0, "date": "2023-03-20T22:09:26.946023", "report": "", "report_sec": "", "report_perf": "", "report_a11y": "", "report_stand": "", "data": "{}"}, {"site_id": 39, "type_of_test": 20, "rating": 4.38, "rating_sec": 4.38, "rating_perf": -1.0, "rating_a11y": -1.0, "rating_stand": -1.0, "date": "2023-03-20T22:09:48.441567", "report": "- The site could be better, but is pretty good.\n- Result generated: 2023-03-20 22:09:40 Etc/UTC (Cached for 24 hours)\n", "report_sec": "- HTTPS by default: is good! ( 5.00 rating )\r\n- HTTP Strict Transport Security HSTS: is good! ( 5.00 rating )\r\n- Content Security Policy: is good! ( 5.00 rating )\r\n- Reporting CSP Certificate Transparency Network Error Logging: is good! ( 5.00 rating )\r\n- Referrer Policy: is good! ( 5.00 rating )\r\n- Subresource Integrity SRI: is pretty bad. ( 1.00 rating )\r\n- HTTP headers: is good! ( 5.00 rating )\r\n- Cookies: is ok, with 2 error(s) and 0 warning(s). ( 4.00 rating )\r\n", "report_perf": "", "report_a11y": "", "report_stand": "", "data": "{}"}, {"site_id": 40, "type_of_test": 20, "rating": 3.69, "rating_sec": 3.69, "rating_perf": -1.0, "rating_a11y": -1.0, "rating_stand": -1.0, "date": "2023-03-20T22:10:09.936846", "report": "- Ok integrity but should get better.\n- Result generated: 2023-03-20 22:10:00 Etc/UTC (Cached for 24 hours)\n", "report_sec": "- HTTPS by default: is good! ( 5.00 rating )\r\n- HTTP Strict Transport Security HSTS: is good! ( 5.00 rating )\r\n- Content Security Policy: is pretty bad. ( 1.00 rating )\r\n- Reporting CSP Certificate Transparency Network Error Logging: is not that good. ( 2.50 rating )\r\n- Referrer Policy: is pretty bad. ( 1.00 rating )\r\n- Subresource Integrity SRI: is good! ( 5.00 rating )\r\n- HTTP headers: is good! ( 5.00 rating )\r\n- Cookies: is good! ( 5.00 rating )\r\n", "report_perf": "", "report_a11y": "", "report_stand": "", "data": "{}"}, {"site_id": 41, "type_of_test": 20, "rating": 2.44, "rating_sec": 2.44, "rating_perf": -1.0, "rating_a11y": -1.0, "rating_stand": -1.0, "date": "2023-03-20T22:10:31.517058", "report": "- Rather poor on user privacy.\n- Result generated: 2023-03-20 22:10:27 Etc/UTC (Cached for 24 hours)\n", "report_sec": "- HTTPS by default: is good! ( 5.00 rating )\r\n- Strict Transport Security: is pretty bad. ( 1.00 rating )\r\n- Content Security Policy: is pretty bad. ( 1.00 rating )\r\n- Reporting CSP Certificate Transparency Network Error Logging: is good! ( 5.00 rating )\r\n- Referrer Policy: is pretty bad. ( 1.00 rating )\r\n- Subresource Integrity SRI: is pretty bad. ( 1.00 rating )\r\n- HTTP headers: is ok, with 1 error(s) and 0 warning(s). ( 4.50 rating )\r\n- Cookies: is ok, with 15 error(s) and 0 warning(s). ( 1.00 rating )\r\n", "report_perf": "", "report_a11y": "", "report_stand": "", "data": "{}"}, {"site_id": 42, "type_of_test": 20, "rating": 3.31, "rating_sec": 3.31, "rating_perf": -1.0, "rating_a11y": -1.0, "rating_stand": -1.0, "date": "2023-03-20T22:10:53.028634", "report": "- Ok integrity but should get better.\n- Result generated: 2023-03-20 22:10:44 Etc/UTC (Cached for 24 hours)\n", "report_sec": "- HTTPS by default: is good! ( 5.00 rating )\r\n- HTTP Strict Transport Security HSTS: is ok, with 2 error(s) and 0 warning(s). ( 4.00 rating )\r\n- Content Security Policy: is pretty bad. ( 1.00 rating )\r\n- Reporting CSP Certificate Transparency Network Error Logging: is good! ( 5.00 rating )\r\n- Referrer Policy: is pretty bad. ( 1.00 rating )\r\n- Subresource Integrity SRI: is pretty bad. ( 1.00 rating )\r\n- HTTP headers: is ok, with 1 error(s) and 0 warning(s). ( 4.50 rating )\r\n- Cookies: is good! ( 5.00 rating )\r\n", "report_perf": "", "report_a11y": "", "report_stand": "", "data": "{}"}, {"site_id": 44, "type_of_test": 20, "rating": 2.44, "rating_sec": 2.44, "rating_perf": -1.0, "rating_a11y": -1.0, "rating_stand": -1.0, "date": "2023-03-20T22:11:14.535774", "report": "- Rather poor on user privacy.\n- Result generated: 2023-03-20 22:11:08 Etc/UTC (Cached for 24 hours)\n", "report_sec": "- HTTPS by default: is good! ( 5.00 rating )\r\n- Strict Transport Security: is pretty bad. ( 1.00 rating )\r\n- Content Security Policy: is pretty bad. ( 1.00 rating )\r\n- Reporting CSP Certificate Transparency Network Error Logging: is good! ( 5.00 rating )\r\n- Referrer Policy: is pretty bad. ( 1.00 rating )\r\n- Subresource Integrity SRI: is pretty bad. ( 1.00 rating )\r\n- HTTP headers: is ok, with 1 error(s) and 0 warning(s). ( 4.50 rating )\r\n- Cookies: is ok, with 9 error(s) and 0 warning(s). ( 1.00 rating )\r\n", "report_perf": "", "report_a11y": "", "report_stand": "", "data": "{}"}, {"site_id": 45, "type_of_test": 20, "rating": 3.31, "rating_sec": 3.31, "rating_perf": -1.0, "rating_a11y": -1.0, "rating_stand": -1.0, "date": "2023-03-20T22:11:36.025834", "report": "- Ok integrity but should get better.\n- Result generated: 2023-03-20 22:11:26 Etc/UTC (Cached for 24 hours)\n", "report_sec": "- HTTPS by default: is good! ( 5.00 rating )\r\n- HTTP Strict Transport Security HSTS: is ok, with 2 error(s) and 0 warning(s). ( 4.00 rating )\r\n- Content Security Policy: is pretty bad. ( 1.00 rating )\r\n- Reporting CSP Certificate Transparency Network Error Logging: is good! ( 5.00 rating )\r\n- Referrer Policy: is pretty bad. ( 1.00 rating )\r\n- Subresource Integrity SRI: is pretty bad. ( 1.00 rating )\r\n- HTTP headers: is ok, with 1 error(s) and 0 warning(s). ( 4.50 rating )\r\n- Cookies: is good! ( 5.00 rating )\r\n", "report_perf": "", "report_a11y": "", "report_stand": "", "data": "{}"}, {"site_id": 46, "type_of_test": 20, "rating": 3.31, "rating_sec": 3.31, "rating_perf": -1.0, "rating_a11y": -1.0, "rating_stand": -1.0, "date": "2023-03-20T22:11:57.525709", "report": "- Ok integrity but should get better.\n- Result generated: 2023-03-20 22:11:48 Etc/UTC (Cached for 24 hours)\n", "report_sec": "- HTTPS by default: is good! ( 5.00 rating )\r\n- HTTP Strict Transport Security HSTS: is ok, with 2 error(s) and 0 warning(s). ( 4.00 rating )\r\n- Content Security Policy: is pretty bad. ( 1.00 rating )\r\n- Reporting CSP Certificate Transparency Network Error Logging: is good! ( 5.00 rating )\r\n- Referrer Policy: is pretty bad. ( 1.00 rating )\r\n- Subresource Integrity SRI: is pretty bad. ( 1.00 rating )\r\n- HTTP headers: is ok, with 1 error(s) and 0 warning(s). ( 4.50 rating )\r\n- Cookies: is good! ( 5.00 rating )\r\n", "report_perf": "", "report_a11y": "", "report_stand": "", "data": "{}"}, {"site_id": 48, "type_of_test": 20, "rating": 2.62, "rating_sec": 2.62, "rating_perf": -1.0, "rating_a11y": -1.0, "rating_stand": -1.0, "date": "2023-03-20T22:12:19.043403", "report": "- Rather poor on user privacy.\n- Result generated: 2023-03-20 22:12:09 Etc/UTC (Cached for 24 hours)\n", "report_sec": "- HTTPS by default: is good! ( 5.00 rating )\r\n- HTTP Strict Transport Security HSTS: is pretty bad. ( 1.00 rating )\r\n- Content Security Policy: is pretty bad. ( 1.00 rating )\r\n- Reporting CSP Certificate Transparency Network Error Logging: is not that good. ( 2.50 rating )\r\n- Referrer Policy: is pretty bad. ( 1.00 rating )\r\n- Subresource Integrity SRI: is pretty bad. ( 1.00 rating )\r\n- HTTP headers: is ok, with 1 error(s) and 0 warning(s). ( 4.50 rating )\r\n- Cookies: is good! ( 5.00 rating )\r\n", "report_perf": "", "report_a11y": "", "report_stand": "", "data": "{}"}, {"site_id": 50, "type_of_test": 20, "rating": 2.12, "rating_sec": 2.12, "rating_perf": -1.0, "rating_a11y": -1.0, "rating_stand": -1.0, "date": "2023-03-20T22:12:40.531497", "report": "- Rather poor on user privacy.\n- Result generated: 2023-03-20 22:12:37 Etc/UTC (Cached for 24 hours)\n", "report_sec": "- HTTPS by default: is good! ( 5.00 rating )\r\n- Strict Transport Security: is pretty bad. ( 1.00 rating )\r\n- Content Security Policy: is pretty bad. ( 1.00 rating )\r\n- Reporting CSP Certificate Transparency Network Error Logging: is not that good. ( 2.50 rating )\r\n- Referrer Policy: is pretty bad. ( 1.00 rating )\r\n- Subresource Integrity SRI: is pretty bad. ( 1.00 rating )\r\n- HTTP headers: is ok, with 1 error(s) and 0 warning(s). ( 4.50 rating )\r\n- Cookies: is ok, with 9 error(s) and 0 warning(s). ( 1.00 rating )\r\n", "report_perf": "", "report_a11y": "", "report_stand": "", "data": "{}"}, {"site_id": 51, "type_of_test": 20, "rating": 4.19, "rating_sec": 4.19, "rating_perf": -1.0, "rating_a11y": -1.0, "rating_stand": -1.0, "date": "2023-03-20T22:13:02.017923", "report": "- The site could be better, but is pretty good.\n- Result generated: 2023-03-20 22:12:52 Etc/UTC (Cached for 24 hours)\n", "report_sec": "- HTTPS by default: is good! ( 5.00 rating )\r\n- HTTP Strict Transport Security HSTS: is good! ( 5.00 rating )\r\n- Content Security Policy: is ok, with 3 error(s) and 0 warning(s). ( 3.50 rating )\r\n- Reporting CSP Certificate Transparency Network Error Logging: is not that good. ( 2.50 rating )\r\n- Referrer Policy: is not that good. ( 2.50 rating )\r\n- Subresource Integrity SRI: is good! ( 5.00 rating )\r\n- HTTP headers: is good! ( 5.00 rating )\r\n- Cookies: is good! ( 5.00 rating )\r\n", "report_perf": "", "report_a11y": "", "report_stand": "", "data": "{}"}]}