{"tests": [{"site_id": 6, "type_of_test": 15, "rating": 5.0, "rating_sec": -1.0, "rating_perf": 5.0, "rating_a11y": -1.0, "rating_stand": -1.0, "date": "2024-04-05T08:07:40.853251", "report": "- The website is really fast!\n ( 5.00 rating )\r\n", "report_sec": "", "report_perf": "- Speedindex: 383\n ( 5.00 rating )\r\n- Loading time: 0.374 sec\n- Number of requests: 6", "report_a11y": "", "report_stand": "", "data": "{\"domcontentloaded\": \"236\", \"firstpaint\": \"382\", \"load\": \"374\", \"firstvisualchange\": \"383\", \"speedindex\": \"383\", \"visualcomplete85\": \"383\", \"lastvisualchange\": \"383\", \"requests\": \"6\"}"}, {"site_id": 7, "type_of_test": 15, "rating": 1.36, "rating_sec": -1.0, "rating_perf": 1.36, "rating_a11y": -1.0, "rating_stand": -1.0, "date": "2024-04-05T08:08:19.563969", "report": "- The website is quite slow.\n ( 1.36 rating )\r\n", "report_sec": "", "report_perf": "- Speedindex: 4140\n ( 1.36 rating )\r\n- Loading time: 1.59s\n- Number of requests: 117", "report_a11y": "", "report_stand": "", "data": "{\"domcontentloaded\": \"770\", \"firstpaint\": \"777\", \"load\": \"1.59s\", \"firstvisualchange\": \"783\", \"speedindex\": 4140, \"visualcomplete85\": \"8.00s\", \"lastvisualchange\": \"8.08s\", \"requests\": \"117\"}"}, {"site_id": 8, "type_of_test": 15, "rating": 2.05, "rating_sec": -1.0, "rating_perf": 2.05, "rating_a11y": -1.0, "rating_stand": -1.0, "date": "2024-04-05T08:09:48.306615", "report": "- The website is quite slow.\n ( 2.05 rating )\r\n", "report_sec": "", "report_perf": "- Speedindex: 3450\n ( 2.05 rating )\r\n- Loading time: 3.62s\n- Number of requests: 176", "report_a11y": "", "report_stand": "", "data": "{\"domcontentloaded\": \"1.10s\", \"firstpaint\": \"981\", \"load\": \"3.62s\", \"firstvisualchange\": \"967\", \"speedindex\": 3450, \"visualcomplete85\": \"5.13s\", \"lastvisualchange\": \"9.55s\", \"requests\": \"176\"}"}, {"site_id": 9, "type_of_test": 15, "rating": 4.84, "rating_sec": -1.0, "rating_perf": 4.84, "rating_a11y": -1.0, "rating_stand": -1.0, "date": "2024-04-05T08:10:21.683236", "report": "- The website is fast.\n ( 4.84 rating )\r\n", "report_sec": "", "report_perf": "- Speedindex: 655\n ( 4.84 rating )\r\n- Loading time: 1.33s\n- Number of requests: 121", "report_a11y": "", "report_stand": "", "data": "{\"domcontentloaded\": \"864\", \"firstpaint\": \"572\", \"load\": \"1.33s\", \"firstvisualchange\": \"583\", \"speedindex\": \"655\", \"visualcomplete85\": \"583\", \"lastvisualchange\": \"2.20s\", \"requests\": \"121\"}"}, {"site_id": 12, "type_of_test": 15, "rating": 3.69, "rating_sec": -1.0, "rating_perf": 3.69, "rating_a11y": -1.0, "rating_stand": -1.0, "date": "2024-04-05T08:10:58.759094", "report": "- About average speed.\n ( 3.69 rating )\r\n", "report_sec": "", "report_perf": "- Speedindex: 1810\n ( 3.69 rating )\r\n- Loading time: 2.53s\n- Number of requests: 47", "report_a11y": "", "report_stand": "", "data": "{\"domcontentloaded\": \"1.50s\", \"firstpaint\": \"1.25s\", \"load\": \"2.53s\", \"firstvisualchange\": \"1.23s\", \"speedindex\": 1810, \"visualcomplete85\": \"1.87s\", \"lastvisualchange\": \"1.87s\", \"requests\": \"47\"}"}, {"site_id": 13, "type_of_test": 15, "rating": 3.59, "rating_sec": -1.0, "rating_perf": 3.59, "rating_a11y": -1.0, "rating_stand": -1.0, "date": "2024-04-05T08:11:35.357767", "report": "- About average speed.\n ( 3.59 rating )\r\n", "report_sec": "", "report_perf": "- Speedindex: 1910\n ( 3.59 rating )\r\n- Loading time: 2.67s\n- Number of requests: 31", "report_a11y": "", "report_stand": "", "data": "{\"domcontentloaded\": \"2.27s\", \"firstpaint\": \"1.86s\", \"load\": \"2.67s\", \"firstvisualchange\": \"1.87s\", \"speedindex\": 1910, \"visualcomplete85\": \"1.92s\", \"lastvisualchange\": \"1.92s\", \"requests\": \"31\"}"}, {"site_id": 16, "type_of_test": 15, "rating": 5.0, "rating_sec": -1.0, "rating_perf": 5.0, "rating_a11y": -1.0, "rating_stand": -1.0, "date": "2024-04-05T08:12:07.069873", "report": "- The website is really fast!\n ( 5.00 rating )\r\n", "report_sec": "", "report_perf": "- Speedindex: 101\n ( 5.00 rating )\r\n- Loading time: 0.201 sec\n- Number of requests: 15", "report_a11y": "", "report_stand": "", "data": "{\"domcontentloaded\": \"143\", \"firstpaint\": \"107\", \"load\": \"201\", \"firstvisualchange\": \"100\", \"speedindex\": \"101\", \"visualcomplete85\": \"100\", \"lastvisualchange\": \"167\", \"requests\": \"15\"}"}, {"site_id": 17, "type_of_test": 15, "rating": 4.23, "rating_sec": -1.0, "rating_perf": 4.23, "rating_a11y": -1.0, "rating_stand": -1.0, "date": "2024-04-05T08:12:41.193441", "report": "- The website is fast.\n ( 4.23 rating )\r\n", "report_sec": "", "report_perf": "- Speedindex: 1270\n ( 4.23 rating )\r\n- Loading time: 1.30s\n- Number of requests: 20", "report_a11y": "", "report_stand": "", "data": "{\"domcontentloaded\": \"1.25s\", \"firstpaint\": \"1.26s\", \"load\": \"1.30s\", \"firstvisualchange\": \"1.25s\", \"speedindex\": 1270, \"visualcomplete85\": \"1.35s\", \"lastvisualchange\": \"1.37s\", \"requests\": \"20\"}"}, {"site_id": 19, "type_of_test": 15, "rating": 5.0, "rating_sec": -1.0, "rating_perf": 5.0, "rating_a11y": -1.0, "rating_stand": -1.0, "date": "2024-04-05T08:13:12.781078", "report": "- The website is really fast!\n ( 5.00 rating )\r\n", "report_sec": "", "report_perf": "- Speedindex: 153\n ( 5.00 rating )\r\n- Loading time: 0.157 sec\n- Number of requests: 48", "report_a11y": "", "report_stand": "", "data": "{\"domcontentloaded\": \"148\", \"firstpaint\": \"148\", \"load\": \"157\", \"firstvisualchange\": \"150\", \"speedindex\": \"153\", \"visualcomplete85\": \"150\", \"lastvisualchange\": \"183\", \"requests\": \"48\"}"}, {"site_id": 21, "type_of_test": 15, "rating": 3.62, "rating_sec": -1.0, "rating_perf": 3.62, "rating_a11y": -1.0, "rating_stand": -1.0, "date": "2024-04-05T08:13:49.408520", "report": "- About average speed.\n ( 3.62 rating )\r\n", "report_sec": "", "report_perf": "- Speedindex: 1880\n ( 3.62 rating )\r\n- Loading time: 2.24s\n- Number of requests: 24", "report_a11y": "", "report_stand": "", "data": "{\"domcontentloaded\": \"1.25s\", \"firstpaint\": \"1.26s\", \"load\": \"2.24s\", \"firstvisualchange\": \"1.27s\", \"speedindex\": 1880, \"visualcomplete85\": \"2.45s\", \"lastvisualchange\": \"2.60s\", \"requests\": \"24\"}"}, {"site_id": 22, "type_of_test": 15, "rating": 3.84, "rating_sec": -1.0, "rating_perf": 3.84, "rating_a11y": -1.0, "rating_stand": -1.0, "date": "2024-04-05T08:14:26.845618", "report": "- About average speed.\n ( 3.84 rating )\r\n", "report_sec": "", "report_perf": "- Speedindex: 1660\n ( 3.84 rating )\r\n- Loading time: 1.47s\n- Number of requests: 78", "report_a11y": "", "report_stand": "", "data": "{\"domcontentloaded\": \"1.10s\", \"firstpaint\": \"1.08s\", \"load\": \"1.47s\", \"firstvisualchange\": \"1.08s\", \"speedindex\": 1660, \"visualcomplete85\": \"2.03s\", \"lastvisualchange\": \"2.42s\", \"requests\": \"78\"}"}, {"site_id": 23, "type_of_test": 15, "rating": 4.95, "rating_sec": -1.0, "rating_perf": 4.95, "rating_a11y": -1.0, "rating_stand": -1.0, "date": "2024-04-05T08:14:58.604316", "report": "- The website is fast.\n ( 4.95 rating )\r\n", "report_sec": "", "report_perf": "- Speedindex: 550\n ( 4.95 rating )\r\n- Loading time: 0.636 sec\n- Number of requests: 20", "report_a11y": "", "report_stand": "", "data": "{\"domcontentloaded\": \"539\", \"firstpaint\": \"537\", \"load\": \"636\", \"firstvisualchange\": \"550\", \"speedindex\": \"550\", \"visualcomplete85\": \"550\", \"lastvisualchange\": \"550\", \"requests\": \"20\"}"}, {"site_id": 24, "type_of_test": 15, "rating": 3.42, "rating_sec": -1.0, "rating_perf": 3.42, "rating_a11y": -1.0, "rating_stand": -1.0, "date": "2024-04-05T08:15:35.040230", "report": "- About average speed.\n ( 3.42 rating )\r\n", "report_sec": "", "report_perf": "- Speedindex: 2080\n ( 3.42 rating )\r\n- Loading time: 2.15s\n- Number of requests: 41", "report_a11y": "", "report_stand": "", "data": "{\"domcontentloaded\": \"1.91s\", \"firstpaint\": \"1.86s\", \"load\": \"2.15s\", \"firstvisualchange\": \"1.85s\", \"speedindex\": 2080, \"visualcomplete85\": \"2.15s\", \"lastvisualchange\": \"2.15s\", \"requests\": \"41\"}"}, {"site_id": 25, "type_of_test": 15, "rating": 1.0, "rating_sec": -1.0, "rating_perf": 1.0, "rating_a11y": -1.0, "rating_stand": -1.0, "date": "2024-04-05T08:21:54.692237", "report": "- The website is very slow!\n ( 1.00 rating )\r\n", "report_sec": "", "report_perf": "- Speedindex: 4830\n ( 1.00 rating )\r\n- Loading time: 134.19s\n- Number of requests: 883", "report_a11y": "", "report_stand": "", "data": "{\"load\": \"134.19s\", \"domcontentloaded\": \"678\", \"firstpaint\": \"311\", \"firstvisualchange\": \"317\", \"speedindex\": 4830, \"visualcomplete85\": \"1.75s\", \"lastvisualchange\": \"113.05s\", \"requests\": \"883\"}"}, {"site_id": 27, "type_of_test": 15, "rating": 5.0, "rating_sec": -1.0, "rating_perf": 5.0, "rating_a11y": -1.0, "rating_stand": -1.0, "date": "2024-04-05T08:22:26.699753", "report": "- The website is really fast!\n ( 5.00 rating )\r\n", "report_sec": "", "report_perf": "- Speedindex: 290\n ( 5.00 rating )\r\n- Loading time: 0.417 sec\n- Number of requests: 23", "report_a11y": "", "report_stand": "", "data": "{\"domcontentloaded\": \"286\", \"firstpaint\": \"277\", \"load\": \"417\", \"firstvisualchange\": \"283\", \"speedindex\": \"290\", \"visualcomplete85\": \"283\", \"lastvisualchange\": \"433\", \"requests\": \"23\"}"}, {"site_id": 28, "type_of_test": 15, "rating": 4.91, "rating_sec": -1.0, "rating_perf": 4.91, "rating_a11y": -1.0, "rating_stand": -1.0, "date": "2024-04-05T08:22:59.631942", "report": "- The website is fast.\n ( 4.91 rating )\r\n", "report_sec": "", "report_perf": "- Speedindex: 588\n ( 4.91 rating )\r\n- Loading time: 0.576 sec\n- Number of requests: 8", "report_a11y": "", "report_stand": "", "data": "{\"domcontentloaded\": \"523\", \"firstpaint\": \"582\", \"load\": \"576\", \"firstvisualchange\": \"583\", \"speedindex\": \"588\", \"visualcomplete85\": \"600\", \"lastvisualchange\": \"600\", \"requests\": \"8\"}"}, {"site_id": 29, "type_of_test": 15, "rating": 4.3, "rating_sec": -1.0, "rating_perf": 4.3, "rating_a11y": -1.0, "rating_stand": -1.0, "date": "2024-04-05T08:23:34.730460", "report": "- The website is fast.\n ( 4.30 rating )\r\n", "report_sec": "", "report_perf": "- Speedindex: 1200\n ( 4.30 rating )\r\n- Loading time: 1.48s\n- Number of requests: 31", "report_a11y": "", "report_stand": "", "data": "{\"domcontentloaded\": \"1.26s\", \"firstpaint\": \"1.17s\", \"load\": \"1.48s\", \"firstvisualchange\": \"1.17s\", \"speedindex\": 1200, \"visualcomplete85\": \"1.20s\", \"lastvisualchange\": \"1.43s\", \"requests\": \"31\"}"}, {"site_id": 30, "type_of_test": 15, "rating": 4.63, "rating_sec": -1.0, "rating_perf": 4.63, "rating_a11y": -1.0, "rating_stand": -1.0, "date": "2024-04-05T08:24:06.310561", "report": "- The website is fast.\n ( 4.63 rating )\r\n", "report_sec": "", "report_perf": "- Speedindex: 867\n ( 4.63 rating )\r\n- Loading time: 1.35s\n- Number of requests: 15", "report_a11y": "", "report_stand": "", "data": "{\"domcontentloaded\": \"864\", \"firstpaint\": \"869\", \"load\": \"1.35s\", \"firstvisualchange\": \"867\", \"speedindex\": \"867\", \"visualcomplete85\": \"867\", \"lastvisualchange\": \"867\", \"requests\": \"15\"}"}, {"site_id": 31, "type_of_test": 15, "rating": 5.0, "rating_sec": -1.0, "rating_perf": 5.0, "rating_a11y": -1.0, "rating_stand": -1.0, "date": "2024-04-05T08:24:40.054958", "report": "- The website is really fast!\n ( 5.00 rating )\r\n", "report_sec": "", "report_perf": "- Speedindex: 477\n ( 5.00 rating )\r\n- Loading time: 0.916 sec\n- Number of requests: 57", "report_a11y": "", "report_stand": "", "data": "{\"domcontentloaded\": \"311\", \"firstpaint\": \"296\", \"load\": \"916\", \"firstvisualchange\": \"316\", \"speedindex\": \"477\", \"visualcomplete85\": \"550\", \"lastvisualchange\": \"550\", \"requests\": \"57\"}"}, {"site_id": 32, "type_of_test": 15, "rating": 3.82, "rating_sec": -1.0, "rating_perf": 3.82, "rating_a11y": -1.0, "rating_stand": -1.0, "date": "2024-04-05T08:25:18.782617", "report": "- About average speed.\n ( 3.82 rating )\r\n", "report_sec": "", "report_perf": "- Speedindex: 1680\n ( 3.82 rating )\r\n- Loading time: 0.767 sec\n- Number of requests: 48", "report_a11y": "", "report_stand": "", "data": "{\"domcontentloaded\": \"499\", \"firstpaint\": \"379\", \"load\": \"767\", \"firstvisualchange\": \"383\", \"speedindex\": 1680, \"visualcomplete85\": \"1.73s\", \"lastvisualchange\": \"6.57s\", \"requests\": \"48\"}"}, {"site_id": 35, "type_of_test": 15, "rating": 4.62, "rating_sec": -1.0, "rating_perf": 4.62, "rating_a11y": -1.0, "rating_stand": -1.0, "date": "2024-04-05T08:25:52.542248", "report": "- The website is fast.\n ( 4.62 rating )\r\n", "report_sec": "", "report_perf": "- Speedindex: 876\n ( 4.62 rating )\r\n- Loading time: 1.04s\n- Number of requests: 36", "report_a11y": "", "report_stand": "", "data": "{\"domcontentloaded\": \"800\", \"firstpaint\": \"805\", \"load\": \"1.04s\", \"firstvisualchange\": \"800\", \"speedindex\": \"876\", \"visualcomplete85\": \"1.05s\", \"lastvisualchange\": \"1.97s\", \"requests\": \"36\"}"}, {"site_id": 36, "type_of_test": 15, "rating": 4.87, "rating_sec": -1.0, "rating_perf": 4.87, "rating_a11y": -1.0, "rating_stand": -1.0, "date": "2024-04-05T08:26:25.286697", "report": "- The website is fast.\n ( 4.87 rating )\r\n", "report_sec": "", "report_perf": "- Speedindex: 631\n ( 4.87 rating )\r\n- Loading time: 0.671 sec\n- Number of requests: 16", "report_a11y": "", "report_stand": "", "data": "{\"domcontentloaded\": \"530\", \"firstpaint\": \"542\", \"load\": \"671\", \"firstvisualchange\": \"533\", \"speedindex\": \"631\", \"visualcomplete85\": \"666\", \"lastvisualchange\": \"666\", \"requests\": \"16\"}"}, {"site_id": 37, "type_of_test": 15, "rating": 5.0, "rating_sec": -1.0, "rating_perf": 5.0, "rating_a11y": -1.0, "rating_stand": -1.0, "date": "2024-04-05T08:26:57.266190", "report": "- The website is really fast!\n ( 5.00 rating )\r\n", "report_sec": "", "report_perf": "- Speedindex: 347\n ( 5.00 rating )\r\n- Loading time: 0.391 sec\n- Number of requests: 22", "report_a11y": "", "report_stand": "", "data": "{\"domcontentloaded\": \"355\", \"firstpaint\": \"331\", \"load\": \"391\", \"firstvisualchange\": \"333\", \"speedindex\": \"347\", \"visualcomplete85\": \"367\", \"lastvisualchange\": \"400\", \"requests\": \"22\"}"}, {"site_id": 39, "type_of_test": 15, "rating": 3.91, "rating_sec": -1.0, "rating_perf": 3.91, "rating_a11y": -1.0, "rating_stand": -1.0, "date": "2024-04-05T08:27:35.325409", "report": "- About average speed.\n ( 3.91 rating )\r\n", "report_sec": "", "report_perf": "- Speedindex: 1590\n ( 3.91 rating )\r\n- Loading time: 1.94s\n- Number of requests: 24", "report_a11y": "", "report_stand": "", "data": "{\"domcontentloaded\": \"1.30s\", \"firstpaint\": \"1.34s\", \"load\": \"1.94s\", \"firstvisualchange\": \"1.35s\", \"speedindex\": 1590, \"visualcomplete85\": \"1.75s\", \"lastvisualchange\": \"2.83s\", \"requests\": \"24\"}"}, {"site_id": 41, "type_of_test": 15, "rating": 4.17, "rating_sec": -1.0, "rating_perf": 4.17, "rating_a11y": -1.0, "rating_stand": -1.0, "date": "2024-04-05T08:28:10.449007", "report": "- The website is fast.\n ( 4.17 rating )\r\n", "report_sec": "", "report_perf": "- Speedindex: 1330\n ( 4.17 rating )\r\n- Loading time: 1.59s\n- Number of requests: 61", "report_a11y": "", "report_stand": "", "data": "{\"domcontentloaded\": \"1.28s\", \"firstpaint\": \"1.27s\", \"load\": \"1.59s\", \"firstvisualchange\": \"1.27s\", \"speedindex\": 1330, \"visualcomplete85\": \"1.33s\", \"lastvisualchange\": \"1.43s\", \"requests\": \"61\"}"}, {"site_id": 42, "type_of_test": 15, "rating": 5.0, "rating_sec": -1.0, "rating_perf": 5.0, "rating_a11y": -1.0, "rating_stand": -1.0, "date": "2024-04-05T08:28:42.449939", "report": "- The website is really fast!\n ( 5.00 rating )\r\n", "report_sec": "", "report_perf": "- Speedindex: 351\n ( 5.00 rating )\r\n- Loading time: 1.02s\n- Number of requests: 84", "report_a11y": "", "report_stand": "", "data": "{\"domcontentloaded\": \"381\", \"firstpaint\": \"292\", \"load\": \"1.02s\", \"firstvisualchange\": \"300\", \"speedindex\": \"351\", \"visualcomplete85\": \"366\", \"lastvisualchange\": \"1.05s\", \"requests\": \"84\"}"}, {"site_id": 44, "type_of_test": 15, "rating": 3.94, "rating_sec": -1.0, "rating_perf": 3.94, "rating_a11y": -1.0, "rating_stand": -1.0, "date": "2024-04-05T08:29:23.416989", "report": "- About average speed.\n ( 3.94 rating )\r\n", "report_sec": "", "report_perf": "- Speedindex: 1560\n ( 3.94 rating )\r\n- Loading time: 1.68s\n- Number of requests: 104", "report_a11y": "", "report_stand": "", "data": "{\"domcontentloaded\": \"713\", \"firstpaint\": \"481\", \"load\": \"1.68s\", \"firstvisualchange\": \"483\", \"speedindex\": 1560, \"visualcomplete85\": \"1.75s\", \"lastvisualchange\": \"3.27s\", \"requests\": \"104\"}"}, {"site_id": 45, "type_of_test": 15, "rating": 5.0, "rating_sec": -1.0, "rating_perf": 5.0, "rating_a11y": -1.0, "rating_stand": -1.0, "date": "2024-04-05T08:29:54.995226", "report": "- The website is really fast!\n ( 5.00 rating )\r\n", "report_sec": "", "report_perf": "- Speedindex: 313\n ( 5.00 rating )\r\n- Loading time: 0.410 sec\n- Number of requests: 33", "report_a11y": "", "report_stand": "", "data": "{\"domcontentloaded\": \"279\", \"firstpaint\": \"279\", \"load\": \"410\", \"firstvisualchange\": \"283\", \"speedindex\": \"313\", \"visualcomplete85\": \"317\", \"lastvisualchange\": \"317\", \"requests\": \"33\"}"}, {"site_id": 46, "type_of_test": 15, "rating": 4.98, "rating_sec": -1.0, "rating_perf": 4.98, "rating_a11y": -1.0, "rating_stand": -1.0, "date": "2024-04-05T08:30:28.585829", "report": "- The website is fast.\n ( 4.98 rating )\r\n", "report_sec": "", "report_perf": "- Speedindex: 518\n ( 4.98 rating )\r\n- Loading time: 0.501 sec\n- Number of requests: 58", "report_a11y": "", "report_stand": "", "data": "{\"domcontentloaded\": \"318\", \"firstpaint\": \"299\", \"load\": \"501\", \"firstvisualchange\": \"300\", \"speedindex\": \"518\", \"visualcomplete85\": \"533\", \"lastvisualchange\": \"533\", \"requests\": \"58\"}"}, {"site_id": 48, "type_of_test": 15, "rating": 4.7, "rating_sec": -1.0, "rating_perf": 4.7, "rating_a11y": -1.0, "rating_stand": -1.0, "date": "2024-04-05T08:31:00.991182", "report": "- The website is fast.\n ( 4.70 rating )\r\n", "report_sec": "", "report_perf": "- Speedindex: 796\n ( 4.70 rating )\r\n- Loading time: 1.02s\n- Number of requests: 12", "report_a11y": "", "report_stand": "", "data": "{\"domcontentloaded\": \"861\", \"firstpaint\": \"722\", \"load\": \"1.02s\", \"firstvisualchange\": \"717\", \"speedindex\": \"796\", \"visualcomplete85\": \"717\", \"lastvisualchange\": \"1.58s\", \"requests\": \"12\"}"}, {"site_id": 51, "type_of_test": 15, "rating": 5.0, "rating_sec": -1.0, "rating_perf": 5.0, "rating_a11y": -1.0, "rating_stand": -1.0, "date": "2024-04-05T08:31:32.933761", "report": "- The website is really fast!\n ( 5.00 rating )\r\n", "report_sec": "", "report_perf": "- Speedindex: 304\n ( 5.00 rating )\r\n- Loading time: 0.309 sec\n- Number of requests: 6", "report_a11y": "", "report_stand": "", "data": "{\"domcontentloaded\": \"154\", \"firstpaint\": \"297\", \"load\": \"309\", \"firstvisualchange\": \"300\", \"speedindex\": \"304\", \"visualcomplete85\": \"300\", \"lastvisualchange\": \"350\", \"requests\": \"6\"}"}, {"site_id": 52, "type_of_test": 15, "rating": 5.0, "rating_sec": -1.0, "rating_perf": 5.0, "rating_a11y": -1.0, "rating_stand": -1.0, "date": "2024-04-05T08:32:05.445725", "report": "- The website is really fast!\n ( 5.00 rating )\r\n", "report_sec": "", "report_perf": "- Speedindex: 343\n ( 5.00 rating )\r\n- Loading time: 0.397 sec\n- Number of requests: 30", "report_a11y": "", "report_stand": "", "data": "{\"domcontentloaded\": \"276\", \"firstpaint\": \"277\", \"load\": \"397\", \"firstvisualchange\": \"267\", \"speedindex\": \"343\", \"visualcomplete85\": \"433\", \"lastvisualchange\": \"583\", \"requests\": \"30\"}"}, {"site_id": 53, "type_of_test": 15, "rating": 4.11, "rating_sec": -1.0, "rating_perf": 4.11, "rating_a11y": -1.0, "rating_stand": -1.0, "date": "2024-04-05T08:32:45.893801", "report": "- The website is fast.\n ( 4.11 rating )\r\n", "report_sec": "", "report_perf": "- Speedindex: 1390\n ( 4.11 rating )\r\n- Loading time: 3.10s\n- Number of requests: 199", "report_a11y": "", "report_stand": "", "data": "{\"domcontentloaded\": \"2.16s\", \"firstpaint\": \"1.31s\", \"load\": \"3.10s\", \"firstvisualchange\": \"1.32s\", \"speedindex\": 1390, \"visualcomplete85\": \"1.32s\", \"lastvisualchange\": \"3.78s\", \"requests\": \"199\"}"}, {"site_id": 54, "type_of_test": 15, "rating": 5.0, "rating_sec": -1.0, "rating_perf": 5.0, "rating_a11y": -1.0, "rating_stand": -1.0, "date": "2024-04-05T08:33:17.752054", "report": "- The website is really fast!\n ( 5.00 rating )\r\n", "report_sec": "", "report_perf": "- Speedindex: 396\n ( 5.00 rating )\r\n- Loading time: 0.856 sec\n- Number of requests: 42", "report_a11y": "", "report_stand": "", "data": "{\"domcontentloaded\": \"407\", \"firstpaint\": \"381\", \"load\": \"856\", \"firstvisualchange\": \"383\", \"speedindex\": \"396\", \"visualcomplete85\": \"383\", \"lastvisualchange\": \"583\", \"requests\": \"42\"}"}, {"site_id": 55, "type_of_test": 15, "rating": 4.65, "rating_sec": -1.0, "rating_perf": 4.65, "rating_a11y": -1.0, "rating_stand": -1.0, "date": "2024-04-05T08:33:51.164665", "report": "- The website is fast.\n ( 4.65 rating )\r\n", "report_sec": "", "report_perf": "- Speedindex: 852\n ( 4.65 rating )\r\n- Loading time: 1.22s\n- Number of requests: 30", "report_a11y": "", "report_stand": "", "data": "{\"domcontentloaded\": \"889\", \"firstpaint\": \"835\", \"load\": \"1.22s\", \"firstvisualchange\": \"833\", \"speedindex\": \"852\", \"visualcomplete85\": \"900\", \"lastvisualchange\": \"917\", \"requests\": \"30\"}"}]}